dash_infra/__init__.py
dash_infra/components/__init__.py
dash_infra/components/download.py
dash_infra/components/figure.py
dash_infra/components/groups.py
dash_infra/components/maps.py
dash_infra/components/storage.py
dash_infra/components/store_user.py
dash_infra/components/table.py
dash_infra/components/upload.py
dash_infra/core/__init__.py
dash_infra/core/callback.py
dash_infra/core/component.py
dash_infra/core/dash_app.py
dash_infra/core/super_app.py
dash_infra/core/assets/dash.css
dash_infra/core/static/custom.css
dash_infra/core/templates/base.html
dash_infra/core/templates/endpoints.html
dash_infra/core/templates/index.html
dash_infra/html_helpers/__init__.py
dash_infra/html_helpers/divs.py
dash_infra/mixins/__init__.py
dash_infra/mixins/json_serializers.py
kws_dash_infra-0.2.7.dist-info/METADATA
kws_dash_infra-0.2.7.dist-info/WHEEL
kws_dash_infra-0.2.7.dist-info/top_level.txt
kws_dash_infra-0.2.7.dist-info/RECORD
