Metadata-Version: 2.1
Name: kws-dash-infra
Version: 0.2.7
Summary: "Helpers to build a dash kws application"
Home-page: UNKNOWN
Author: Mathias Ngo
License: kilowattsol
Platform: UNKNOWN
Classifier: Programming Language :: Python :: 3.7
Classifier: License :: Other/Proprietary License
Requires-Dist: dash (==1.10.0)
Requires-Dist: numpy
Requires-Dist: pandas
Requires-Dist: python-slugify
Provides-Extra: deploy
Requires-Dist: twine ; extra == 'deploy'
Provides-Extra: dev
Requires-Dist: black ; extra == 'dev'
Requires-Dist: rope ; extra == 'dev'
Requires-Dist: ipython ; extra == 'dev'
Requires-Dist: isort ; extra == 'dev'
Requires-Dist: mypy ; extra == 'dev'
Requires-Dist: pre-commit ; extra == 'dev'
Requires-Dist: pytest ; extra == 'dev'
Provides-Extra: docs
Requires-Dist: sphinx ; extra == 'docs'
Requires-Dist: sphinx-autodoc-typehints ; extra == 'docs'
Provides-Extra: examples
Requires-Dist: seaborn ; extra == 'examples'
Provides-Extra: test
Requires-Dist: pytest ; extra == 'test'
Requires-Dist: pytest-cov ; extra == 'test'
